htmltools/__init__.py
htmltools/_core.py
htmltools/_jsx.py
htmltools/_util.py
htmltools/_versions.py
htmltools/py.typed
htmltools/svg.py
htmltools/tags.py
htmltools/lib/react/react.production.min.js
htmltools/lib/react-dom/react-dom.production.min.js
htmltools-0.6.0.dist-info/LICENSE
htmltools-0.6.0.dist-info/METADATA
htmltools-0.6.0.dist-info/WHEEL
htmltools-0.6.0.dist-info/top_level.txt
htmltools-0.6.0.dist-info/RECORD
