Metadata-Version: 2.1
Name: htmltools
Version: 0.6.0
Summary: Tools for HTML generation and output.
Author-email: Carson Sievert <carson@rstudio.com>
License: MIT License
Project-URL: Bug Tracker, https://github.com/rstudio/py-htmltools/issues
Project-URL: Source, https://github.com/rstudio/py-htmltools
Keywords: html
Classifier: Development Status :: 5 - Production/Stable
Classifier: Intended Audience :: Developers
Classifier: License :: OSI Approved :: MIT License
Classifier: Programming Language :: Python
Classifier: Programming Language :: Python :: 3.9
Classifier: Programming Language :: Python :: 3.10
Classifier: Programming Language :: Python :: 3.11
Classifier: Programming Language :: Python :: 3.12
Classifier: Programming Language :: Python :: Implementation :: PyPy
Classifier: Topic :: Internet :: WWW/HTTP :: Dynamic Content
Classifier: Topic :: Software Development :: Libraries :: Python Modules
Classifier: Topic :: Text Processing :: Markup :: HTML
Requires-Python: >=3.9
License-File: LICENSE
Requires-Dist: typing-extensions>=3.10.0.0
Requires-Dist: packaging>=20.9
Provides-Extra: test
Requires-Dist: pytest>=6.2.4; extra == "test"
Requires-Dist: syrupy>=4.6.0; extra == "test"
Provides-Extra: dev
Requires-Dist: black>=24.2.0; extra == "dev"
Requires-Dist: flake8>=6.0.0; extra == "dev"
Requires-Dist: Flake8-pyproject; extra == "dev"
Requires-Dist: isort>=5.11.2; extra == "dev"
Requires-Dist: pyright>=1.1.348; extra == "dev"
Requires-Dist: pre-commit>=2.15.0; extra == "dev"
Requires-Dist: wheel; extra == "dev"
Requires-Dist: build; extra == "dev"
